rtaspi/__init__.py
rtaspi/__main__.py
rtaspi/_version.py
rtaspi/main.py
rtaspi/api/__init__.py
rtaspi/api/devices.py
rtaspi/api/pipelines.py
rtaspi/api/server.py
rtaspi/api/streams.py
rtaspi/cli/__init__.py
rtaspi/cli/shell.py
rtaspi/cli/commands/__init__.py
rtaspi/cli/commands/config.py
rtaspi/cli/commands/devices.py
rtaspi/cli/commands/pipelines.py
rtaspi/cli/commands/server.py
rtaspi/cli/commands/streams.py
rtaspi/config/__init__.py
rtaspi/constants/__init__.py
rtaspi/constants/camera.py
rtaspi/constants/detection.py
rtaspi/constants/devices.py
rtaspi/constants/filters.py
rtaspi/constants/logging.py
rtaspi/constants/outputs.py
rtaspi/constants/protocols.py
rtaspi/constants/resolutions.py
rtaspi/constants/streaming.py
rtaspi/core/__init__.py
rtaspi/core/config.py
rtaspi/core/defaults.py
rtaspi/core/enums.py
rtaspi/core/logging.py
rtaspi/core/mcp.py
rtaspi/core/rtaspi.py
rtaspi/core/utils.py
rtaspi/device_managers/__init__.py
rtaspi/device_managers/base.py
rtaspi/device_managers/command_handler.py
rtaspi/device_managers/local_devices.py
rtaspi/device_managers/network_devices.py
rtaspi/device_managers/stream_manager.py
rtaspi/device_managers/remote_desktop/__init__.py
rtaspi/device_managers/remote_desktop/base.py
rtaspi/device_managers/remote_desktop/capture.py
rtaspi/device_managers/remote_desktop/manager.py
rtaspi/device_managers/remote_desktop/rdp.py
rtaspi/device_managers/remote_desktop/vnc.py
rtaspi/device_managers/scanners/__init__.py
rtaspi/device_managers/scanners/base.py
rtaspi/device_managers/scanners/linux_scanner.py
rtaspi/device_managers/scanners/macos_scanner.py
rtaspi/device_managers/scanners/windows_scanner.py
rtaspi/device_managers/utils/__init__.py
rtaspi/device_managers/utils/device.py
rtaspi/device_managers/utils/discovery.py
rtaspi/device_managers/utils/protocols.py
rtaspi/dsl/__init__.py
rtaspi/dsl/executor.py
rtaspi/dsl/lexer.py
rtaspi/dsl/parser.py
rtaspi/processing/__init__.py
rtaspi/processing/pipeline_executor.py
rtaspi/quick/__init__.py
rtaspi-0.1.39.dist-info/licenses/LICENSE
rtaspi-0.1.39.dist-info/METADATA
rtaspi-0.1.39.dist-info/WHEEL
rtaspi-0.1.39.dist-info/entry_points.txt
rtaspi-0.1.39.dist-info/top_level.txt
rtaspi-0.1.39.dist-info/RECORD
